flowws_freud/LocalDensity.py
flowws_freud/RDF.py
flowws_freud/SmoothBOD.py
flowws_freud/Steinhardt.py
flowws_freud/__init__.py
flowws_freud/version.py
flowws_freud-0.3.0.dist-info/LICENSE
flowws_freud-0.3.0.dist-info/METADATA
flowws_freud-0.3.0.dist-info/WHEEL
flowws_freud-0.3.0.dist-info/entry_points.txt
flowws_freud-0.3.0.dist-info/top_level.txt
flowws_freud-0.3.0.dist-info/RECORD
