Metadata-Version: 2.1
Name: flowws-freud
Version: 0.3.0
Summary: Stage-based scientific workflows using freud
Home-page: UNKNOWN
Author: Matthew Spellings
Author-email: matthew.p.spellings@gmail.com
License: MIT
Platform: UNKNOWN
Classifier: Development Status :: 3 - Alpha
Classifier: License :: OSI Approved :: MIT License
Classifier: Programming Language :: Python :: 3
Requires-Python: >=3
Requires-Dist: flowws
Requires-Dist: freud-analysis
